{"errors":[],"warnings":[],"namedChunkGroups":{"polyfill":{"chunks":[3,0,8],"assets":["webpack-runtime-aec0cbcf1ae8ab4bbc65.js","webpack-runtime-aec0cbcf1ae8ab4bbc65.js.map","commons-7d569d3428ffe1ba092a.js","commons-7d569d3428ffe1ba092a.js.map","polyfill-b3cdf4efa4860a9f5b07.js","polyfill-b3cdf4efa4860a9f5b07.js.map"],"children":{},"childAssets":{}},"app":{"chunks":[3,7,4],"assets":["webpack-runtime-aec0cbcf1ae8ab4bbc65.js","webpack-runtime-aec0cbcf1ae8ab4bbc65.js.map","framework-83e11af5cf111be5ad89.js","framework-83e11af5cf111be5ad89.js.map","app-b6046fc758eade846047.js","app-b6046fc758eade846047.js.map"],"children":{},"childAssets":{}},"component---src-pages-404-js":{"chunks":[2,1,0,5],"assets":["styles.cadc0530c832470f90ff.css","styles-7d4153d260c0197f0043.js","styles-7d4153d260c0197f0043.js.map","5e2a4920-92a603aa382fb44ef956.js","5e2a4920-92a603aa382fb44ef956.js.map","commons-7d569d3428ffe1ba092a.js","commons-7d569d3428ffe1ba092a.js.map","component---src-pages-404-js-f37998f02672b25c479a.js","component---src-pages-404-js-f37998f02672b25c479a.js.map"],"children":{},"childAssets":{}},"component---src-pages-index-js":{"chunks":[2,1,0,6],"assets":["styles.cadc0530c832470f90ff.css","styles-7d4153d260c0197f0043.js","styles-7d4153d260c0197f0043.js.map","5e2a4920-92a603aa382fb44ef956.js","5e2a4920-92a603aa382fb44ef956.js.map","commons-7d569d3428ffe1ba092a.js","commons-7d569d3428ffe1ba092a.js.map","component---src-pages-index-js-bf66c4d09faa68decd62.js","component---src-pages-index-js-bf66c4d09faa68decd62.js.map"],"children":{},"childAssets":{}}},"assetsByChunkName":{"polyfill":["webpack-runtime-aec0cbcf1ae8ab4bbc65.js","commons-7d569d3428ffe1ba092a.js","polyfill-b3cdf4efa4860a9f5b07.js"],"app":["webpack-runtime-aec0cbcf1ae8ab4bbc65.js","framework-83e11af5cf111be5ad89.js","app-b6046fc758eade846047.js"],"component---src-pages-404-js":["styles.cadc0530c832470f90ff.css","styles-7d4153d260c0197f0043.js","5e2a4920-92a603aa382fb44ef956.js","commons-7d569d3428ffe1ba092a.js","component---src-pages-404-js-f37998f02672b25c479a.js"],"component---src-pages-index-js":["styles.cadc0530c832470f90ff.css","styles-7d4153d260c0197f0043.js","5e2a4920-92a603aa382fb44ef956.js","commons-7d569d3428ffe1ba092a.js","component---src-pages-index-js-bf66c4d09faa68decd62.js"]}}